dj_active_campaign/__init__.py
dj_active_campaign/__version__.py
dj_active_campaign/admin.py
dj_active_campaign/apps.py
dj_active_campaign/config.py
dj_active_campaign/forms.py
dj_active_campaign/integrations.py
dj_active_campaign/models.py
dj_active_campaign/urls.py
dj_active_campaign/views.py
dj_active_campaign/active_campaign/__init__.py
dj_active_campaign/active_campaign/connector.py
dj_active_campaign/active_campaign/contact.py
dj_active_campaign/active_campaign/custom_field.py
dj_active_campaign/api/__init__.py
dj_active_campaign/api/v1/__init__.py
dj_active_campaign/api/v1/urls.py
dj_active_campaign/api/v1/views.py
dj_active_campaign/migrations/0001_initial.py
dj_active_campaign/migrations/__init__.py
dj_active_campaign/templates/dj_active_campaign/custom_fields.html
dj_active_campaign/templates/dj_active_campaign/index.html
dj_active_campaign-0.0.9.dist-info/LICENSE
dj_active_campaign-0.0.9.dist-info/METADATA
dj_active_campaign-0.0.9.dist-info/WHEEL
dj_active_campaign-0.0.9.dist-info/top_level.txt
dj_active_campaign-0.0.9.dist-info/RECORD
