Metadata-Version: 2.1
Name: dj-active-campaign
Version: 0.0.9
Summary: A Django Implementation of the Active Campaign Python SDK
Author-email: Roberto Himmelbauer <robertoh89@gmail.com>
Project-URL: Homepage, https://github.com/rhimmelbauer/django-active-campaign
Project-URL: Bug Tracker, https://github.com/rhimmelbauer/django-active-campaign/issues
Keywords: django,app
Classifier: Programming Language :: Python :: 3 :: Only
Classifier: License :: OSI Approved :: MIT License
Classifier: Operating System :: OS Independent
Requires-Python: >=3.7
License-File: LICENSE
Requires-Dist: Django (<4.0,>=3)
Requires-Dist: django-autoslug
Requires-Dist: django-site-configs
Requires-Dist: django-integrations
Provides-Extra: dev
Requires-Dist: dj-database-url ; extra == 'dev'
Requires-Dist: psycopg2-binary ; extra == 'dev'
Requires-Dist: django-allauth ; extra == 'dev'
Requires-Dist: django-crispy-forms ; extra == 'dev'
Requires-Dist: toml ; extra == 'dev'
Provides-Extra: docs
Requires-Dist: recommonmark ; extra == 'docs'
Requires-Dist: m2r ; extra == 'docs'
Requires-Dist: django-extensions ; extra == 'docs'
Requires-Dist: coverage ; extra == 'docs'
Requires-Dist: Sphinx ; extra == 'docs'
Requires-Dist: rstcheck ; extra == 'docs'
Requires-Dist: sphinx-rtd-theme ; extra == 'docs'
